multicorr.py
multicorr-0.0.1.dist-info/LICENSE
multicorr-0.0.1.dist-info/METADATA
multicorr-0.0.1.dist-info/WHEEL
multicorr-0.0.1.dist-info/top_level.txt
multicorr-0.0.1.dist-info/RECORD
